Workbook

Sheet Start Here
B2: BalanceBuddy import template
B3: Template version 1 · upload this file to BalanceBuddy to add accounts, promos and balances in one go.
B5: Accounts | C5: One row per card or loan. Set these up once; update only when something changes (new APR, new limit, closed).
B6: Promo Balances | C6: One row per promo-rate PART of a balance: balance transfers, 0% intro purchases, deferred-interest store financing. A card can have several. The rest of the balance is charged the standard APR.
B7: Balance Update | C7: The quick monthly sheet. One row per account per date. Copy your account list down, set the date, type today's balances, upload. Old rows can stay; the app keeps them as history and ignores exact duplicates.
B9: Colour key
B10: Soft yellow cells | C10: Type here.
B11: Darker header | C11: Required column.
B12: Lighter header | C12: Optional column.
B13: Grey-green header | C13: Calculated by the sheet. Don't edit; the app ignores these columns on upload.
B14: Grey italic row | C14: An example. Leave it or delete it; rows whose nickname is EXAMPLE are skipped on upload.
B16: Rules
B17: Account nickname | C17: The link between sheets. Must be unique and match exactly (capitals and spaces count).
B18: Percentages | C18: Type 24.99% (with the % sign) or 0.2499.
B19: Money | C19: Plain numbers, no $ needed. Balances you owe are positive.
B20: Dates | C20: Any date Excel or Google Sheets understands; shown as yyyy-mm-dd.
B21: Card numbers | C21: Never enter a full card or account number. Last 4 is optional.
B22: Don't rename | C22: Keep sheet names and header text as they are, or the upload can't match columns. You can add your own columns to the right; they'll be ignored.
B23: Google Sheets | C23: Works there too: File › Import this .xlsx, then File › Download › Microsoft Excel (.xlsx) to upload.

Sheet Accounts
A1: Account nickname | B1: Owner | C1: Issuer | D1: Product name | E1: Account type | F1: Network | G1: Last 4 (optional) | H1: Credit limit / original loan ($) | I1: Standard APR | J1: Statement closing day | K1: Closing day approximate? (Y/N) | L1: Payment due day | M1: Fixed minimum payment ($) | N1: Autopay amount ($) | O1: Status | P1: Notes
A2: EXAMPLE | B2: Me | C2: Chase | D2: Freedom | E2: Credit card | F2: Visa | G2: 6349 | H2: 2400 | I2: 0.2074 | J2: 18 | K2: N | L2: 15 | N2: 40 | O2: Open | P2: Example row: skipped on upload

Sheet Promo Balances
A1: Account nickname | B1: Promo type | C1: Promo balance ($) | D1: Promo APR | E1: Promo start date | F1: Promo end date | G1: Fee charged ($) | H1: Notes | I1: Check
A2: EXAMPLE | B2: Balance transfer | C2: 3000 | D2: 0 | E2: 46082 | F2: 46568 | G2: 90 | H2: Example row: skipped on upload | I2: =IF(A2="","",IF(A2="EXAMPLE","example",IF(COUNTIF(Accounts!$A$2:$A$500,A2)=0,"Not in Accounts",IF(F2="","Add end date",IF(F2<TODAY(),"Expired",(F2-TODAY())&" days left"))))) -> example
I3: =IF(A3="","",IF(A3="EXAMPLE","example",IF(COUNTIF(Accounts!$A$2:$A$500,A3)=0,"Not in Accounts",IF(F3="","Add end date",IF(F3<TODAY(),"Expired",(F3-TODAY())&" days left")))))
I4: =IF(A4="","",IF(A4="EXAMPLE","example",IF(COUNTIF(Accounts!$A$2:$A$500,A4)=0,"Not in Accounts",IF(F4="","Add end date",IF(F4<TODAY(),"Expired",(F4-TODAY())&" days left")))))
I5: =IF(A5="","",IF(A5="EXAMPLE","example",IF(COUNTIF(Accounts!$A$2:$A$500,A5)=0,"Not in Accounts",IF(F5="","Add end date",IF(F5<TODAY(),"Expired",(F5-TODAY())&" days left")))))
I6: =IF(A6="","",IF(A6="EXAMPLE","example",IF(COUNTIF(Accounts!$A$2:$A$500,A6)=0,"Not in Accounts",IF(F6="","Add end date",IF(F6<TODAY(),"Expired",(F6-TODAY())&" days left")))))
I7: =IF(A7="","",IF(A7="EXAMPLE","example",IF(COUNTIF(Accounts!$A$2:$A$500,A7)=0,"Not in Accounts",IF(F7="","Add end date",IF(F7<TODAY(),"Expired",(F7-TODAY())&" days left")))))
I8: =IF(A8="","",IF(A8="EXAMPLE","example",IF(COUNTIF(Accounts!$A$2:$A$500,A8)=0,"Not in Accounts",IF(F8="","Add end date",IF(F8<TODAY(),"Expired",(F8-TODAY())&" days left")))))
I9: =IF(A9="","",IF(A9="EXAMPLE","example",IF(COUNTIF(Accounts!$A$2:$A$500,A9)=0,"Not in Accounts",IF(F9="","Add end date",IF(F9<TODAY(),"Expired",(F9-TODAY())&" days left")))))
I10: =IF(A10="","",IF(A10="EXAMPLE","example",IF(COUNTIF(Accounts!$A$2:$A$500,A10)=0,"Not in Accounts",IF(F10="","Add end date",IF(F10<TODAY(),"Expired",(F10-TODAY())&" days left")))))
I11: =IF(A11="","",IF(A11="EXAMPLE","example",IF(COUNTIF(Accounts!$A$2:$A$500,A11)=0,"Not in Accounts",IF(F11="","Add end date",IF(F11<TODAY(),"Expired",(F11-TODAY())&" days left")))))
I12: =IF(A12="","",IF(A12="EXAMPLE","example",IF(COUNTIF(Accounts!$A$2:$A$500,A12)=0,"Not in Accounts",IF(F12="","Add end date",IF(F12<TODAY(),"Expired",(F12-TODAY())&" days left")))))
I13: =IF(A13="","",IF(A13="EXAMPLE","example",IF(COUNTIF(Accounts!$A$2:$A$500,A13)=0,"Not in Accounts",IF(F13="","Add end date",IF(F13<TODAY(),"Expired",(F13-TODAY())&" days left")))))
I14: =IF(A14="","",IF(A14="EXAMPLE","example",IF(COUNTIF(Accounts!$A$2:$A$500,A14)=0,"Not in Accounts",IF(F14="","Add end date",IF(F14<TODAY(),"Expired",(F14-TODAY())&" days left")))))
... I500: =IF(A500="","",IF(A500="EXAMPLE","example",IF(COUNTIF(Accounts!$A$2:$A$500,A500)=0,"Not in Accounts",IF(F500="","Add end date",IF(F500<TODAY(),"Expired",(F500-TODAY())&" days left")))))

Sheet Balance Update
A1: As-of date | B1: Account nickname | C1: Current balance ($) | D1: Last statement balance ($) | E1: Minimum due this cycle ($) | F1: Next due date | G1: Notes | H1: Check | I1: Utilization
A2: 46303 | B2: EXAMPLE | C2: 1840.25 | D2: 2061.1 | E2: 40 | F2: 46310 | G2: Example row: skipped on upload | H2: =IF(B2="","",IF(B2="EXAMPLE","example",IF(COUNTIF(Accounts!$A$2:$A$500,B2)=0,"Not in Accounts",IF(C2="","Add balance",IF(A2="","Add date","OK"))))) -> example | I2: =IF(OR(B2="",C2=""),"",IFERROR(C2/INDEX(Accounts!$H$2:$H$500,MATCH(B2,Accounts!$A$2:$A$500,0)),"")) -> 0.76677083
H3: =IF(B3="","",IF(B3="EXAMPLE","example",IF(COUNTIF(Accounts!$A$2:$A$500,B3)=0,"Not in Accounts",IF(C3="","Add balance",IF(A3="","Add date","OK"))))) | I3: =IF(OR(B3="",C3=""),"",IFERROR(C3/INDEX(Accounts!$H$2:$H$500,MATCH(B3,Accounts!$A$2:$A$500,0)),""))
H4: =IF(B4="","",IF(B4="EXAMPLE","example",IF(COUNTIF(Accounts!$A$2:$A$500,B4)=0,"Not in Accounts",IF(C4="","Add balance",IF(A4="","Add date","OK"))))) | I4: =IF(OR(B4="",C4=""),"",IFERROR(C4/INDEX(Accounts!$H$2:$H$500,MATCH(B4,Accounts!$A$2:$A$500,0)),""))
H5: =IF(B5="","",IF(B5="EXAMPLE","example",IF(COUNTIF(Accounts!$A$2:$A$500,B5)=0,"Not in Accounts",IF(C5="","Add balance",IF(A5="","Add date","OK"))))) | I5: =IF(OR(B5="",C5=""),"",IFERROR(C5/INDEX(Accounts!$H$2:$H$500,MATCH(B5,Accounts!$A$2:$A$500,0)),""))
H6: =IF(B6="","",IF(B6="EXAMPLE","example",IF(COUNTIF(Accounts!$A$2:$A$500,B6)=0,"Not in Accounts",IF(C6="","Add balance",IF(A6="","Add date","OK"))))) | I6: =IF(OR(B6="",C6=""),"",IFERROR(C6/INDEX(Accounts!$H$2:$H$500,MATCH(B6,Accounts!$A$2:$A$500,0)),""))
H7: =IF(B7="","",IF(B7="EXAMPLE","example",IF(COUNTIF(Accounts!$A$2:$A$500,B7)=0,"Not in Accounts",IF(C7="","Add balance",IF(A7="","Add date","OK"))))) | I7: =IF(OR(B7="",C7=""),"",IFERROR(C7/INDEX(Accounts!$H$2:$H$500,MATCH(B7,Accounts!$A$2:$A$500,0)),""))
H8: =IF(B8="","",IF(B8="EXAMPLE","example",IF(COUNTIF(Accounts!$A$2:$A$500,B8)=0,"Not in Accounts",IF(C8="","Add balance",IF(A8="","Add date","OK"))))) | I8: =IF(OR(B8="",C8=""),"",IFERROR(C8/INDEX(Accounts!$H$2:$H$500,MATCH(B8,Accounts!$A$2:$A$500,0)),""))
H9: =IF(B9="","",IF(B9="EXAMPLE","example",IF(COUNTIF(Accounts!$A$2:$A$500,B9)=0,"Not in Accounts",IF(C9="","Add balance",IF(A9="","Add date","OK"))))) | I9: =IF(OR(B9="",C9=""),"",IFERROR(C9/INDEX(Accounts!$H$2:$H$500,MATCH(B9,Accounts!$A$2:$A$500,0)),""))
H10: =IF(B10="","",IF(B10="EXAMPLE","example",IF(COUNTIF(Accounts!$A$2:$A$500,B10)=0,"Not in Accounts",IF(C10="","Add balance",IF(A10="","Add date","OK"))))) | I10: =IF(OR(B10="",C10=""),"",IFERROR(C10/INDEX(Accounts!$H$2:$H$500,MATCH(B10,Accounts!$A$2:$A$500,0)),""))
H11: =IF(B11="","",IF(B11="EXAMPLE","example",IF(COUNTIF(Accounts!$A$2:$A$500,B11)=0,"Not in Accounts",IF(C11="","Add balance",IF(A11="","Add date","OK"))))) | I11: =IF(OR(B11="",C11=""),"",IFERROR(C11/INDEX(Accounts!$H$2:$H$500,MATCH(B11,Accounts!$A$2:$A$500,0)),""))
H12: =IF(B12="","",IF(B12="EXAMPLE","example",IF(COUNTIF(Accounts!$A$2:$A$500,B12)=0,"Not in Accounts",IF(C12="","Add balance",IF(A12="","Add date","OK"))))) | I12: =IF(OR(B12="",C12=""),"",IFERROR(C12/INDEX(Accounts!$H$2:$H$500,MATCH(B12,Accounts!$A$2:$A$500,0)),""))
H13: =IF(B13="","",IF(B13="EXAMPLE","example",IF(COUNTIF(Accounts!$A$2:$A$500,B13)=0,"Not in Accounts",IF(C13="","Add balance",IF(A13="","Add date","OK"))))) | I13: =IF(OR(B13="",C13=""),"",IFERROR(C13/INDEX(Accounts!$H$2:$H$500,MATCH(B13,Accounts!$A$2:$A$500,0)),""))
H14: =IF(B14="","",IF(B14="EXAMPLE","example",IF(COUNTIF(Accounts!$A$2:$A$500,B14)=0,"Not in Accounts",IF(C14="","Add balance",IF(A14="","Add date","OK"))))) | I14: =IF(OR(B14="",C14=""),"",IFERROR(C14/INDEX(Accounts!$H$2:$H$500,MATCH(B14,Accounts!$A$2:$A$500,0)),""))
... H500: =IF(B500="","",IF(B500="EXAMPLE","example",IF(COUNTIF(Accounts!$A$2:$A$500,B500)=0,"Not in Accounts",IF(C500="","Add balance",IF(A500="","Add date","OK"))))) | I500: =IF(OR(B500="",C500=""),"",IFERROR(C500/INDEX(Accounts!$H$2:$H$500,MATCH(B500,Accounts!$A$2:$A$500,0)),""))

Sheet Lists
A1: Account type | B1: Network | C1: Closing day approximate? (Y/N) | D1: Status | E1: Promo type
A2: Credit card | B2: Visa | C2: Y | D2: Open | E2: Balance transfer
A3: Store card | B3: Mastercard | C3: N | D3: Paid off (open) | E3: Intro purchase APR
A4: Personal loan | B4: Amex | D4: Closed | E4: Deferred interest
A5: Student loan | B5: Discover | E5: Other promo
A6: Auto loan | B6: Store only
A7: Mortgage | B7: n/a
A8: Line of credit
A9: Other loan
